LICENSE
MANIFEST.in
README.md
setup.py
htmotor/__init__.py
htmotor/html.py
htmotor.egg-info/PKG-INFO
htmotor.egg-info/SOURCES.txt
htmotor.egg-info/dependency_links.txt
htmotor.egg-info/top_level.txt