Metadata-Version: 2.1
Name: htmotor
Version: 1.0.0
Summary: ✈️ HTML Template engine for python!
Home-page: https://github.com/5elenay/htmotor/
Author: 5elenay
Author-email: 
License: MIT
Project-URL: Bug Tracker, https://github.com/5elenay/htmotor/issues
Keywords: template,html,engine,template-engine,view-engine
Platform: UNKNOWN
Classifier: Development Status :: 5 - Production/Stable
Classifier: Intended Audience :: Developers
Classifier: Operating System :: OS Independent
Classifier: License :: OSI Approved :: MIT License
Classifier: Programming Language :: Python :: 3
License-File: LICENSE
